pyomyo/Classifier.py
pyomyo/__init__.py
pyomyo/pyomyo.py
pyomyo-0.0.5.dist-info/LICENSE
pyomyo-0.0.5.dist-info/METADATA
pyomyo-0.0.5.dist-info/WHEEL
pyomyo-0.0.5.dist-info/top_level.txt
pyomyo-0.0.5.dist-info/RECORD
