Metadata-Version: 2.1
Name: pyomyo
Version: 0.0.5
Summary: Python Opensource Myo library
Home-page: https://github.com/PerlinWarp/pyomyo
Author: PerlinWarp
Author-email: PerlinWarp+Myo@gmail.com
License: UNKNOWN
Project-URL: Bug Tracker, https://github.com/PerlinWarp/pyomyo/issues
Platform: UNKNOWN
Classifier: Programming Language :: Python :: 3
Classifier: License :: OSI Approved :: MIT License
Classifier: Operating System :: OS Independent
Requires-Python: >=3.6
License-File: LICENSE
